harte/__init__.py
harte/harte.lark
harte/harte.py
harte/interval.py
harte/mappings.py
harte/parse_harte.py
harte/utils.py
test/__init__.py
test/test_harte.py
test/test_interval.py
harte_library-0.4.5.dist-info/LICENSE
harte_library-0.4.5.dist-info/METADATA
harte_library-0.4.5.dist-info/WHEEL
harte_library-0.4.5.dist-info/top_level.txt
harte_library-0.4.5.dist-info/RECORD
