Metadata-Version: 2.1
Name: harte-library
Version: 0.4.5
Summary: Library for parsing Harte chords and converting them to Music21
Author: Andrea Poltronieri
Classifier: Programming Language :: Python :: 3
Classifier: License :: OSI Approved :: MIT License
Classifier: Operating System :: OS Independent
Requires-Python: >=3.7
License-File: LICENSE
Requires-Dist: music21
Requires-Dist: numpy
Requires-Dist: lark
